roman.py
Roman_Numerals_Simple-1.0.1.dist-info/LICENSE
Roman_Numerals_Simple-1.0.1.dist-info/METADATA
Roman_Numerals_Simple-1.0.1.dist-info/WHEEL
Roman_Numerals_Simple-1.0.1.dist-info/top_level.txt
Roman_Numerals_Simple-1.0.1.dist-info/RECORD
