Metadata-Version: 2.1
Name: Roman-Numerals-Simple
Version: 1.0.1
Summary: Library for interacting with roman numerals
Home-page: https://github.com/gaming32/roman-numerals
Author: Gaming32
Author-email: gaming32i64@gmail.com
License: License :: OSI Approved :: MIT License
Platform: UNKNOWN
